{
  "levelNumber" : 1,
  "playerWireLength" : 3000.0,
  "playerCoins" : 25,
  "packetLoss" : 0.0,
  "gameTime" : 7.3701307,
  "totalPacketsSpawned" : 2,
  "packetsLost" : 0,
  "isProgressiveMode" : true,
  "systems" : [ {
    "type" : "ReferenceSystem",
    "@id" : 1,
    "id" : "source_system",
    "position" : {
      "x" : 273.6,
      "y" : 384.8,
      "hash" : 0
    },
    "inputPorts" : [ ],
    "outputPorts" : [ {
      "@id" : 2,
      "id" : "source_out",
      "type" : "OUTPUT",
      "shape" : "SQUARE",
      "position" : {
        "x" : 387.6,
        "y" : 418.8,
        "hash" : 0
      },
      "attachedConnection" : {
        "@id" : 3,
        "startPort" : 2,
        "endPort" : {
          "@id" : 4,
          "id" : "vpn_a_in",
          "type" : "INPUT",
          "shape" : "SQUARE",
          "position" : {
            "x" : 510.80000000000007,
            "y" : 431.59999999999997,
            "hash" : 0
          },
          "attachedConnection" : 3
        },
        "bendPoints" : [ ],
        "pathPoints" : [ {
          "x" : 393.6,
          "y" : 424.8,
          "hash" : 0
        }, {
          "x" : 516.8000000000001,
          "y" : 437.59999999999997,
          "hash" : 0
        } ]
      }
    } ],
    "packetBuffer" : [ ],
    "justArrivedPackets" : [ ]
  }, {
    "type" : "VPNSystem",
    "@id" : 5,
    "id" : "VPN_A",
    "position" : {
      "x" : 516.8000000000001,
      "y" : 397.59999999999997,
      "hash" : 0
    },
    "inputPorts" : [ 4 ],
    "outputPorts" : [ {
      "@id" : 6,
      "id" : "vpn_a_out",
      "type" : "OUTPUT",
      "shape" : "SQUARE",
      "position" : {
        "x" : 630.8000000000001,
        "y" : 431.59999999999997,
        "hash" : 0
      },
      "attachedConnection" : {
        "@id" : 7,
        "startPort" : 6,
        "endPort" : {
          "@id" : 8,
          "id" : "sab_a_in",
          "type" : "INPUT",
          "shape" : "SQUARE",
          "position" : {
            "x" : 750.0,
            "y" : 424.4,
            "hash" : 0
          },
          "attachedConnection" : 7
        },
        "bendPoints" : [ ],
        "pathPoints" : [ {
          "x" : 636.8000000000001,
          "y" : 437.59999999999997,
          "hash" : 0
        }, {
          "x" : 756.0,
          "y" : 430.4,
          "hash" : 0
        } ]
      }
    } ],
    "packetBuffer" : [ ],
    "justArrivedPackets" : [ ]
  }, {
    "type" : "SaboteurSystem",
    "@id" : 9,
    "id" : "SABOTEUR_A",
    "position" : {
      "x" : 756.0,
      "y" : 390.4,
      "hash" : 0
    },
    "inputPorts" : [ 8 ],
    "outputPorts" : [ {
      "@id" : 10,
      "id" : "sab_a_out",
      "type" : "OUTPUT",
      "shape" : "SQUARE",
      "position" : {
        "x" : 870.0,
        "y" : 424.4,
        "hash" : 0
      },
      "attachedConnection" : {
        "@id" : 11,
        "startPort" : 10,
        "endPort" : {
          "@id" : 12,
          "id" : "dest_in",
          "type" : "INPUT",
          "shape" : "SQUARE",
          "position" : {
            "x" : 944.4,
            "y" : 420.4000000000001,
            "hash" : 0
          },
          "attachedConnection" : 11
        },
        "bendPoints" : [ ],
        "pathPoints" : [ {
          "x" : 876.0,
          "y" : 430.4,
          "hash" : 0
        }, {
          "x" : 950.4,
          "y" : 426.4000000000001,
          "hash" : 0
        } ]
      }
    } ],
    "packetBuffer" : [ ],
    "justArrivedPackets" : [ ],
    "random" : {
      "deprecated" : false
    }
  }, {
    "type" : "ReferenceSystem",
    "@id" : 13,
    "id" : "destination_system",
    "position" : {
      "x" : 950.4,
      "y" : 386.4000000000001,
      "hash" : 0
    },
    "inputPorts" : [ 12 ],
    "outputPorts" : [ ],
    "packetBuffer" : [ ],
    "justArrivedPackets" : [ ]
  } ],
  "packets" : [ {
    "packetType" : "ProtectedPacket",
    "@id" : 14,
    "position" : {
      "x" : 918.1282828740857,
      "y" : 428.13503855515677,
      "hash" : 0
    },
    "currentConnection" : 11,
    "destinationPort" : 12,
    "currentSpeed" : 110.0,
    "noise" : 0.0,
    "size" : 6,
    "path" : [ {
      "x" : 876.0,
      "y" : 430.4,
      "hash" : 0
    }, {
      "x" : 950.4,
      "y" : 426.4000000000001,
      "hash" : 0
    } ],
    "currentPathIndex" : 0,
    "originalPacket" : {
      "packetType" : "TrianglePacket",
      "@id" : 15,
      "position" : {
        "x" : 516.8000000000001,
        "y" : 437.59999999999997,
        "hash" : 0
      },
      "currentConnection" : null,
      "destinationPort" : null,
      "currentSpeed" : 126.93393500000003,
      "noise" : 0.0,
      "size" : 3,
      "path" : [ {
        "x" : 393.6,
        "y" : 424.8,
        "hash" : 0
      }, {
        "x" : 516.8000000000001,
        "y" : 437.59999999999997,
        "hash" : 0
      } ],
      "currentPathIndex" : 1,
      "isAccelerating" : true,
      "coinValue" : 3,
      "visualPosition" : {
        "x" : 516.8000000000001,
        "y" : 437.59999999999997,
        "hash" : 0
      }
    },
    "coinValue" : 3,
    "visualPosition" : {
      "x" : 918.1282828740857,
      "y" : 428.13503855515677,
      "hash" : 0
    }
  } ],
  "packetsToRemove" : [ ],
  "connections" : [ 3, 7, 11 ],
  "spawnEvents" : [ ],
  "packetsSucceeded" : 1,
  "activePowerUps" : [ ],
  "largePacketRegistry" : { },
  "sourceSystem" : 1,
  "destinationSystem" : 13
}